craterdata/__init__.py
craterdata/__main__.py
craterdata/mooncraterdataset.py
craterdata-0.1.3.dist-info/LICENSE
craterdata-0.1.3.dist-info/METADATA
craterdata-0.1.3.dist-info/WHEEL
craterdata-0.1.3.dist-info/top_level.txt
craterdata-0.1.3.dist-info/RECORD
